signal_rs-0.2.51.dist-info/METADATA
signal_rs-0.2.51.dist-info/WHEEL
signal_rs/__init__.py
signal_rs/signal_rs.cpython-311-aarch64-linux-gnu.so
signal_rs-0.2.51.dist-info/RECORD
