Metadata-Version: 2.4
Name: signal_rs
Version: 0.2.51
Requires-Dist: pandas >=2.2.3
Requires-Dist: polars >=1.19
Requires-Dist: pyarrow >=17.0.0
Requires-Dist: plotly >=5.24.1
Requires-Dist: kaleido >=1.0.0rc0
Requires-Dist: cffi
Summary: A signal analysis library written in Rust
Author-email: fabian <fabian.lieb@peptech.de>
License: MIT
Requires-Python: >=3.11
